downpress/__init__.py
downpress/convert.py
downpress-0.2.0.dist-info/WHEEL
downpress-0.2.0.dist-info/entry_points.txt
downpress-0.2.0.dist-info/METADATA
downpress-0.2.0.dist-info/RECORD
