Metadata-Version: 2.3
Name: DownPress
Version: 0.2.0
Summary: DownPress extracts posts and pages from a WordPress export v1.2
Author: Daniel Terhorst-North
Author-email: Daniel Terhorst-North <daniel@dannorth.net>
Requires-Dist: lxml>=6.0.2
Requires-Dist: markdownify>=1.2.2
Requires-Python: >=3.13
